{
  "hash": "5816f6e6",
  "configHash": "a78e41e2",
  "lockfileHash": "dfda0cb5",
  "browserHash": "52aa2805",
  "optimized": {
    "react": {
      "src": "../../node_modules/react/index.js",
      "file": "react.js",
      "fileHash": "99f1bac7",
      "needsInterop": true
    },
    "react-dom/client": {
      "src": "../../node_modules/react-dom/client.js",
      "file": "react-dom_client.js",
      "fileHash": "6ea3bbb7",
      "needsInterop": true
    }
  },
  "chunks": {
    "chunk-GFWMZNU4": {
      "file": "chunk-GFWMZNU4.js"
    }
  }
}